cocotb_bus/__init__.py
cocotb_bus/_version.py
cocotb_bus/bus.py
cocotb_bus/scoreboard.py
cocotb_bus/drivers/__init__.py
cocotb_bus/drivers/amba.py
cocotb_bus/drivers/avalon.py
cocotb_bus/drivers/opb.py
cocotb_bus/drivers/xgmii.py
cocotb_bus/monitors/__init__.py
cocotb_bus/monitors/avalon.py
cocotb_bus/monitors/xgmii.py
cocotb_bus-0.1.1.dist-info/LICENSE
cocotb_bus-0.1.1.dist-info/METADATA
cocotb_bus-0.1.1.dist-info/WHEEL
cocotb_bus-0.1.1.dist-info/top_level.txt
cocotb_bus-0.1.1.dist-info/RECORD
