Metadata-Version: 2.1
Name: cocotb-bus
Version: 0.1.1
Summary: UNKNOWN
Home-page: https://github.com/cocotb/cocotb-bus
Author: cocotb maintainers
Author-email: cocotb@lists.librecores.org
License: UNKNOWN
Platform: UNKNOWN
Requires-Python: >=3.5
Requires-Dist: cocotb (<2.0,>=1.5.0.dev)
